antonioso-image-processing/__init__.py
antonioso-image-processing/processing/__init__.py
antonioso-image-processing/processing/combination.py
antonioso-image-processing/processing/filter.py
antonioso-image-processing/processing/transformation.py
antonioso-image-processing/utils/__init__.py
antonioso-image-processing/utils/io.py
antonioso-image-processing/utils/plot.py
antonioso_image_processing/__init__.py
antonioso_image_processing/processing/__init__.py
antonioso_image_processing/processing/combination.py
antonioso_image_processing/processing/filter.py
antonioso_image_processing/processing/transformation.py
antonioso_image_processing/utils/__init__.py
antonioso_image_processing/utils/io.py
antonioso_image_processing/utils/plot.py
image_processing/__init__.py
image_processing/processing/__init__.py
image_processing/processing/combination.py
image_processing/processing/transformation.py
image_processing/utils/__init__.py
image_processing/utils/io.py
image_processing/utils/plot.py
antonioso_image_processing-0.0.6.dist-info/METADATA
antonioso_image_processing-0.0.6.dist-info/WHEEL
antonioso_image_processing-0.0.6.dist-info/top_level.txt
antonioso_image_processing-0.0.6.dist-info/RECORD
