Metadata-Version: 2.4
Name: antonioso-image-processing
Version: 0.0.6
Summary: Package test of image processing
Home-page: https://github.com/MiguelScofielD/image_processing_package
Author: Antonio
Requires-Python: >=3.8
Requires-Dist: numpy
Requires-Dist: matplotlib
Requires-Dist: scikit-image
Requires-Dist: opencv-python
Dynamic: author
Dynamic: description
Dynamic: description-content-type
Dynamic: home-page
Dynamic: requires-dist
Dynamic: requires-python
Dynamic: summary
